virtparade/__init__.py
virtparade/__main__.py
virtparade/args.py
virtparade/utils/__init__.py
virtparade/utils/jinja2.py
virtparade/utils/logger.py
virtparade/utils/num.py
virtparade/utils/objects.py
virtparade/utils/setting.py
virtparade/utils/strings.py
virtparade/utils/system.py
virtparade/utils/time.py
virtparade-0.1.5.data/scripts/virtparade
virtparade-0.1.5.dist-info/LICENSE
virtparade-0.1.5.dist-info/METADATA
virtparade-0.1.5.dist-info/WHEEL
virtparade-0.1.5.dist-info/top_level.txt
virtparade-0.1.5.dist-info/RECORD
