Metadata-Version: 2.1
Name: virtparade
Version: 0.1.5
Summary: An easy-use tool help you create kvm virtual machines gracefully with simple configuration on Linux servers.
Home-page: https://github.com/major1201/virtparade
Author: major1201
Author-email: major1201@gmail.com
License: private
Platform: UNKNOWN
Classifier: Development Status :: 3 - Alpha
Classifier: Intended Audience :: Developers
Classifier: Topic :: Software Development :: Build Tools
Classifier: License :: OSI Approved :: MIT License
Classifier: Programming Language :: Python :: 3
Classifier: Programming Language :: Python :: 3.4
Classifier: Programming Language :: Python :: 3.5
Classifier: Programming Language :: Python :: 3.6
Requires-Python: >=3.4
Requires-Dist: Jinja2
Requires-Dist: MarkupSafe
Requires-Dist: PyYAML
Requires-Dist: six
